[
    {
        "id": 1,
        "titulo": "Treino 1 de Segunda-feira",
        "texto": "📍 **SEGUNDA-FEIRA** \n### Mobilidade de Ombro e Quadril \nEste treino foi projetado para trabalhar a mobilidade dos ombros e quadris, preparando o corpo para os movimentos de força e resistência que seguem. O aquecimento é fundamental para prevenir lesões e melhorar o desempenho ao longo do treino. \n### Aquecimento \nO aquecimento consiste em 2 rounds de exercícios variados que ativam diferentes grupos musculares, como mostrado abaixo: \n- 1 Shuttle run \n- 10 Med ball push up \n- 2 Shuttle run - Modo de fazer: <https://www.youtube.com/watch?v=ZyiZCDgqHKk> \n- 15 Tall med ball clean \n- 3 Shuttle Run \n- 20 Med ball sit up \n### Força - Squat Clean \nA seção de força foca no **Squat Clean**, onde você realizará 7 rounds com intervalos de 1 minuto e 20 segundos entre cada round. A progressão de carga é descrita a seguir: \n- No 1° e 2° round: 5 repetições com 50% a 60% da sua carga máxima \n- No 3° e 4° round: 3 repetições com 70% a 75% \n- No 5° e 6° round: 2 repetições com 80% a 85% \n- No 7° round: 1 repetição com 90% \n### Técnica \nNeste treino, a técnica enfatizada é o **Hand Release Push Up**. Esse movimento ajuda a garantir a execução correta das flexões, promovendo força e estabilidade no core e nos ombros. \n### WOD (Workout of the Day) \n**FOR TIME: (Cap 14’)** \nO WOD é composto por 3 rounds de: \n- 12 Kb overhead lunge (24/16) \n- 9 Hand release push up \n- 6 Clean* \n*Após cada round, adicione 5% na carga do Clean. \nRepita a sequência para mais 3 rounds, como descrito abaixo: \n- 12 Kb overhead lunge (24/16) \n- 9 Hand release push up \n- 6 Clean* \n**Sc:** Barbell (progression) \n**Rx:** Barbell (60% e 65%) \nEste treino oferece uma combinação eficaz de força, técnica e resistência, ideal para quem busca melhorar o desempenho no CrossFit. Com a progressão adequada de cargas e foco na técnica, você poderá evoluir em cada movimento, alcançando novos níveis de condicionamento. \nCaso queira acessar mais treinos como este, confira nosso site para detalhes e programas adicionais.",
        "diaId": 2
    },
    {
        "id": 2,
        "titulo": "Treino 2 de Segunda-feira",
        "texto": "Conteúdo do treino 2 para segunda-feira...",
        "diaId": 2
    },
    {
        "id": 3,
        "titulo": "Treino 1 de Terça-feira",
        "texto": "Conteúdo do Treino 1 de Terça-feira...",
        "diaId": 3
    },
    {
        "id": 4,
        "titulo": "Treino 2 de Terça-feira",
        "texto": "Conteúdo do treino 2 para terça-feira...",
        "diaId": 3
    },
    {
        "id": 5,
        "titulo": "Treino 1 de Quarta-feira",
        "texto": "Conteúdo do treino 1 para Quarta-feira...",
        "diaId": 4
    },
    {
        "id": 6,
        "titulo": "Treino 2 de Quarta-feira",
        "texto": "Conteúdo do treino 2 para Quarta-feira...",
        "diaId": 4
    },
    {
        "id": 7,
        "titulo": "Treino 1 de Quinta-feira",
        "texto": "Conteúdo do Treino 1 de Quinta-feira...",
        "diaId": 5
    },
    {
        "id": 8,
        "titulo": "Treino 1 de Quinta-feira",
        "texto": "Conteúdo do treino 1 para Quinta-feira...",
        "diaId": 5
    }
]
